simpleurllib3.py
simpleurllib3-0.1.5.dist-info/LICENSE
simpleurllib3-0.1.5.dist-info/METADATA
simpleurllib3-0.1.5.dist-info/WHEEL
simpleurllib3-0.1.5.dist-info/top_level.txt
simpleurllib3-0.1.5.dist-info/RECORD
