Metadata-Version: 2.1
Name: simpleurllib3
Version: 0.1.5
Summary: Easy to use urllib3 simplifier.
Home-page: UNKNOWN
Author: TriC
License: UNKNOWN
Keywords: urllib3,requests,simple,http
Platform: UNKNOWN
Classifier: Programming Language :: Python :: 3
Classifier: License :: OSI Approved :: MIT License
Classifier: Operating System :: OS Independent
Requires-Python: >= 3.6
